ini_helper/__init__.py
ini_helper/utils.py
ini_helper-0.0.2.dist-info/LICENSE
ini_helper-0.0.2.dist-info/METADATA
ini_helper-0.0.2.dist-info/WHEEL
ini_helper-0.0.2.dist-info/top_level.txt
ini_helper-0.0.2.dist-info/RECORD
