Metadata-Version: 2.1
Name: ini-helper
Version: 0.0.2
Summary: A ini R/W package
Author: W.M
Author-email: python_zhong@qq.com
License: UNKNOWN
Platform: UNKNOWN
Classifier: Programming Language :: Python :: 3
Classifier: License :: OSI Approved :: MIT License
Classifier: Operating System :: OS Independent
Requires-Python: >=3.6
License-File: LICENSE
